torman/Utils.py
torman/__init__.py
torman/__main__.py
torman/app.py
torman/reset-ip.py
torman/start-tor.py
torman-0.0.6.dist-info/LICENSE
torman-0.0.6.dist-info/METADATA
torman-0.0.6.dist-info/WHEEL
torman-0.0.6.dist-info/entry_points.txt
torman-0.0.6.dist-info/top_level.txt
torman-0.0.6.dist-info/RECORD
