Metadata-Version: 2.1
Name: torman
Version: 0.0.6
Summary: Initialize multiple TOR instances and proxy to them using an API
Home-page: UNKNOWN
Author: Anthony Mugendi
Author-email: ngurumugz@gmail.com
License: Apache License 2.0
Keywords: python,tor,manager,proxy,multiple,anonymous
Platform: any
Classifier: Development Status :: 5 - Production/Stable
Classifier: Intended Audience :: Developers
Classifier: Intended Audience :: System Administrators
Classifier: Intended Audience :: Telecommunications Industry
Classifier: Operating System :: OS Independent
Classifier: Programming Language :: Python :: 2
Classifier: Programming Language :: Python :: 3
Classifier: Programming Language :: Python :: Implementation :: PyPy
Classifier: Topic :: Internet
Classifier: Topic :: System :: Networking
Requires-Dist: coloredlogs
Requires-Dist: fastcore
Requires-Dist: Flask
Requires-Dist: psutil
Requires-Dist: requests
Requires-Dist: setuptools
Requires-Dist: stem
Requires-Dist: waitress
